pydantic_form/__about__.py
pydantic_form/__init__.py
pydantic_form-0.0.1.dist-info/METADATA
pydantic_form-0.0.1.dist-info/WHEEL
pydantic_form-0.0.1.dist-info/licenses/LICENSE
pydantic_form-0.0.1.dist-info/licenses/LICENSE.txt
pydantic_form-0.0.1.dist-info/RECORD
