Metadata-Version: 2.1
Name: pydantic-form
Version: 0.0.1
Summary: JSON-Schema Form generator using pydantic
Project-URL: Documentation, https://github.com/unknown/pydantic-form#readme
Project-URL: Issues, https://github.com/unknown/pydantic-form/issues
Project-URL: Source, https://github.com/unknown/pydantic-form
Author-email: chaojie <zhuzhezhe95@gmail.com>
Keywords: form,json-schema,pydantic
Classifier: Development Status :: 4 - Beta
Classifier: Programming Language :: Python
Classifier: Programming Language :: Python :: 3.7
Classifier: Programming Language :: Python :: 3.8
Classifier: Programming Language :: Python :: 3.9
Classifier: Programming Language :: Python :: 3.10
Classifier: Programming Language :: Python :: Implementation :: CPython
Classifier: Programming Language :: Python :: Implementation :: PyPy
Requires-Python: >=3.7
Requires-Dist: pydantic
